skmd/__init__.py
skmd/circuit.py
skmd/data.py
skmd/extract.py
skmd/network.py
skmd/plot.py
skmd/signals.py
skmd/structure.py
scikit_microwave_design-0.1.1.dist-info/LICENSE
scikit_microwave_design-0.1.1.dist-info/METADATA
scikit_microwave_design-0.1.1.dist-info/WHEEL
scikit_microwave_design-0.1.1.dist-info/top_level.txt
scikit_microwave_design-0.1.1.dist-info/RECORD
